paymob/__init__.py
paymob/http.py
paymob/http_mixins.py
paymob/logging.py
paymob/utils.py
paymob/web_hooks.py
paymob/accept/__init__.py
paymob/accept/exceptions.py
paymob/accept/api/__init__.py
paymob/accept/api/confirm_moto.py
paymob/accept/api/customer.py
paymob/accept/api/intention.py
paymob/accept/api/payment_reference.py
paymob-1.0.0.dist-info/LICENSE
paymob-1.0.0.dist-info/METADATA
paymob-1.0.0.dist-info/WHEEL
paymob-1.0.0.dist-info/top_level.txt
paymob-1.0.0.dist-info/RECORD
