Metadata-Version: 2.1
Name: paymob
Version: 1.0.0
Summary: Paymob FLASH SDK
Home-page: https://github.com/PaymobAccept/paymob-python
Author: Paymob
Author-email: menessy@paymob.com
License: UNKNOWN
Project-URL: Documentation, https://docs.paymob.com
Platform: UNKNOWN
Classifier: Programming Language :: Python :: 3
Classifier: License :: OSI Approved :: MIT License
Classifier: Operating System :: OS Independent
Requires-Python: >=3.6
License-File: LICENSE
Requires-Dist: requests
